fops/__init__.py
fops/__main__.py
fops/_cli_entry.py
fops/cli.py
fops/commands/__init__.py
fops/commands/create_archive.py
fops/commands/delete_branches.py
fops/commands/delete_cache.py
fops/commands/rename_extensions.py
fops/core.py
fops/utils.py
fops-0.1.0rc4.dist-info/WHEEL
fops-0.1.0rc4.dist-info/entry_points.txt
fops-0.1.0rc4.dist-info/METADATA
fops-0.1.0rc4.dist-info/RECORD
