Metadata-Version: 2.3
Name: fops
Version: 0.1.0rc4
Summary: 
Author: oyghen
Author-email: oyghen <oyghen@duck.com>
Requires-Dist: typer>=0.21.0 ; extra == 'cli'
Requires-Python: >=3.11
Provides-Extra: cli
